seano_formatter_qa_notes/__init__.py
seano_formatter_qa_notes/qa_notes.py
seano_formatter_qa_notes/shared/__init__.py
seano_formatter_qa_notes/shared/components.py
seano_formatter_qa_notes/shared/hlist.py
seano_formatter_qa_notes/shared/html_buf.py
seano_formatter_qa_notes/shared/links.py
seano_formatter_qa_notes/shared/markup.py
seano_formatter_qa_notes/shared/metacache.py
seano_formatter_qa_notes/shared/schema_painting.py
seano_formatter_qa_notes/shared/schema_plumbing.py
seano_formatter_qa_notes/shared/text_buf.py
seano_formatter_qa_notes-2.0.2.dist-info/LICENSE
seano_formatter_qa_notes-2.0.2.dist-info/METADATA
seano_formatter_qa_notes-2.0.2.dist-info/WHEEL
seano_formatter_qa_notes-2.0.2.dist-info/top_level.txt
seano_formatter_qa_notes-2.0.2.dist-info/RECORD
